easyGauge/__inti__.py
easyGauge/easyGauge.py
easyGauge-1.0.0.dist-info/LICENSE
easyGauge-1.0.0.dist-info/METADATA
easyGauge-1.0.0.dist-info/WHEEL
easyGauge-1.0.0.dist-info/top_level.txt
easyGauge-1.0.0.dist-info/RECORD
