Metadata-Version: 2.1
Name: easyGauge
Version: 1.0.0
Summary: Reusable Streamlit component for quickly deploying Plotly indicator gauge charts.
Author-email: Derek Evans <derek.evans@deinfoservice.com>
Project-URL: Homepage, https://www.techbyderek.com
Classifier: Programming Language :: Python :: 3
Classifier: License :: OSI Approved :: MIT License
Classifier: Operating System :: OS Independent
Requires-Python: >=3.7
License-File: LICENSE
